pyprofiler/__init__.py
pyprofiler/__main__.py
pyprofiler/cli.py
pyprofiler/printer.py
pyprofiler/profiler.py
pyprofiler/utils.py
simple_pyprofiler-2024.0.1.dist-info/METADATA
simple_pyprofiler-2024.0.1.dist-info/WHEEL
simple_pyprofiler-2024.0.1.dist-info/entry_points.txt
simple_pyprofiler-2024.0.1.dist-info/top_level.txt
simple_pyprofiler-2024.0.1.dist-info/RECORD
