Metadata-Version: 2.1
Name: simple-pyprofiler
Version: 2024.0.1
Summary: Easy profiler for python functions
Author: Joakim Loxdal
Author-email: loxdal@proton.me
Project-URL: Repository, https://github.com/mrkickling/pyprofiler.git
Requires-Python: >=3.8
Requires-Dist: PyYAML ~=6.0
